CUP_Network/__config__.py
CUP_Network/__init__.py
CUP_Network/main.py
CUP_Network-0.0.15.dist-info/LICENSE
CUP_Network-0.0.15.dist-info/METADATA
CUP_Network-0.0.15.dist-info/WHEEL
CUP_Network-0.0.15.dist-info/entry_points.txt
CUP_Network-0.0.15.dist-info/top_level.txt
CUP_Network-0.0.15.dist-info/zip-safe
CUP_Network-0.0.15.dist-info/RECORD
