Metadata-Version: 2.1
Name: CUP-Network
Version: 0.0.15
Summary: Draw Mtx As Thumbnail
Home-page: https://github.com/Rhythmicc/CUP_Network
Author: RhythmLian
Author-email: RhythmLian@outlook.com
License: MIT
Classifier: Programming Language :: Python :: 3
Classifier: License :: OSI Approved :: MIT License
Classifier: Operating System :: OS Independent
License-File: LICENSE
Requires-Dist: selenium
Requires-Dist: Qpro
